HowtodoinjavaSpringJiaochengChuyiFix1/README.md
HowtodoinjavaSpringJiaochengChuyiFix1/__init__.py
HowtodoinjavaSpringJiaochengChuyiFix1/__main__.py
HowtodoinjavaSpringJiaochengChuyiFix1/file.epub
HowtodoinjavaSpringJiaochengChuyiFix1/index.html
HowtodoinjavaSpringJiaochengChuyiFix1/css/__init__.py
HowtodoinjavaSpringJiaochengChuyiFix1/css/annotations.css
HowtodoinjavaSpringJiaochengChuyiFix1/css/main.css
HowtodoinjavaSpringJiaochengChuyiFix1/css/normalize.css
HowtodoinjavaSpringJiaochengChuyiFix1/css/popup.css
HowtodoinjavaSpringJiaochengChuyiFix1/font/__init__.py
HowtodoinjavaSpringJiaochengChuyiFix1/font/fontello.eot
HowtodoinjavaSpringJiaochengChuyiFix1/font/fontello.svg
HowtodoinjavaSpringJiaochengChuyiFix1/font/fontello.ttf
HowtodoinjavaSpringJiaochengChuyiFix1/font/fontello.woff
HowtodoinjavaSpringJiaochengChuyiFix1/img/__init__.py
HowtodoinjavaSpringJiaochengChuyiFix1/img/annotator-glyph-sprite.png
HowtodoinjavaSpringJiaochengChuyiFix1/img/annotator-icon-sprite.png
HowtodoinjavaSpringJiaochengChuyiFix1/img/apple-touch-icon.png
HowtodoinjavaSpringJiaochengChuyiFix1/img/cancelfullscreen.png
HowtodoinjavaSpringJiaochengChuyiFix1/img/close.png
HowtodoinjavaSpringJiaochengChuyiFix1/img/fullscreen.png
HowtodoinjavaSpringJiaochengChuyiFix1/img/loader.gif
HowtodoinjavaSpringJiaochengChuyiFix1/img/menu-icon.png
HowtodoinjavaSpringJiaochengChuyiFix1/img/save.png
HowtodoinjavaSpringJiaochengChuyiFix1/img/saved.png
HowtodoinjavaSpringJiaochengChuyiFix1/img/settings-s.png
HowtodoinjavaSpringJiaochengChuyiFix1/img/settings.png
HowtodoinjavaSpringJiaochengChuyiFix1/img/star.png
HowtodoinjavaSpringJiaochengChuyiFix1/js/__init__.py
HowtodoinjavaSpringJiaochengChuyiFix1/js/epub.js
HowtodoinjavaSpringJiaochengChuyiFix1/js/epub.min.js
HowtodoinjavaSpringJiaochengChuyiFix1/js/epub.min.map
HowtodoinjavaSpringJiaochengChuyiFix1/js/hooks.min.js
HowtodoinjavaSpringJiaochengChuyiFix1/js/hooks.min.map
HowtodoinjavaSpringJiaochengChuyiFix1/js/reader.js
howtodoinjava_spring_jiaocheng_chuyi_fix1-2025.3.24.1.dist-info/METADATA
howtodoinjava_spring_jiaocheng_chuyi_fix1-2025.3.24.1.dist-info/WHEEL
howtodoinjava_spring_jiaocheng_chuyi_fix1-2025.3.24.1.dist-info/entry_points.txt
howtodoinjava_spring_jiaocheng_chuyi_fix1-2025.3.24.1.dist-info/top_level.txt
howtodoinjava_spring_jiaocheng_chuyi_fix1-2025.3.24.1.dist-info/RECORD
